redis_timers/__init__.py
redis_timers/handler.py
redis_timers/lock.py
redis_timers/py.typed
redis_timers/router.py
redis_timers/settings.py
redis_timers/timers.py
redis_timers/types.py
redis_timers-0.4.1.dist-info/WHEEL
redis_timers-0.4.1.dist-info/METADATA
redis_timers-0.4.1.dist-info/RECORD
