Metadata-Version: 2.4
Name: redis-timers
Version: 0.4.1
Summary: 
Author: Artur Shiriev
Author-email: Artur Shiriev <me@shiriev.ru>
License-Expression: MIT
Requires-Dist: pydantic
Requires-Dist: redis
Requires-Python: >=3.13, <4
